{
	"Version": 3,
	"Meta": {
		"Duration": 8.983,
		"Fps": 60.0,
		"Loop": true,
		"AreBeziersRestricted": true,
		"CurveCount": 48,
		"TotalSegmentCount": 122,
		"TotalPointCount": 336,
		"UserDataCount": 0,
		"TotalUserDataSize": 0
	},
	"Curves": [
		{
			"Target": "Parameter",
			"Id": "Param",
			"Segments": [
				0,
				0,
				1,
				0.261,
				0,
				0.522,
				1,
				0.783,
				1,
				1,
				1.222,
				1,
				1.661,
				0.939,
				2.1,
				0.939,
				1,
				2.45,
				0.939,
				2.8,
				1,
				3.15,
				1,
				1,
				3.539,
				1,
				3.928,
				0.939,
				4.317,
				0.939,
				1,
				4.561,
				0.939,
				4.806,
				1,
				5.05,
				1,
				1,
				5.472,
				1,
				5.894,
				0.939,
				6.317,
				0.939,
				1,
				6.622,
				0.939,
				6.928,
				1,
				7.233,
				1,
				1,
				7.483,
				1,
				7.733,
				0,
				7.983,
				0,
				1,
				8.317,
				0,
				8.65,
				0,
				8.983,
				0
			]
		},
		{
			"Target": "Parameter",
			"Id": "Param7",
			"Segments": [
				0,
				0,
				1,
				2.994,
				0,
				5.989,
				0,
				8.983,
				0
			]
		},
		{
			"Target": "Parameter",
			"Id": "Param5",
			"Segments": [
				0,
				0,
				0,
				7.983,
				0,
				1,
				8.317,
				0,
				8.65,
				0,
				8.983,
				0
			]
		},
		{
			"Target": "Parameter",
			"Id": "Param6",
			"Segments": [
				0,
				0,
				0,
				7.983,
				0,
				1,
				8.317,
				0,
				8.65,
				0,
				8.983,
				0
			]
		},
		{
			"Target": "Parameter",
			"Id": "Param2",
			"Segments": [
				0,
				0,
				1,
				2.661,
				0,
				5.322,
				0,
				7.983,
				0,
				1,
				8.317,
				0,
				8.65,
				0,
				8.983,
				0
			]
		},
		{
			"Target": "Parameter",
			"Id": "ParamHairSide5",
			"Segments": [
				0,
				0,
				0,
				7.983,
				0,
				1,
				8.317,
				0,
				8.65,
				0,
				8.983,
				0
			]
		},
		{
			"Target": "Parameter",
			"Id": "ParamHairSide6",
			"Segments": [
				0,
				0,
				0,
				7.983,
				0,
				1,
				8.317,
				0,
				8.65,
				0,
				8.983,
				0
			]
		},
		{
			"Target": "Parameter",
			"Id": "ParamHairSide8",
			"Segments": [
				0,
				0,
				0,
				8.983,
				0
			]
		},
		{
			"Target": "Parameter",
			"Id": "ParamHairSide9",
			"Segments": [
				0,
				0,
				0,
				8.983,
				0
			]
		},
		{
			"Target": "Parameter",
			"Id": "ParamHairSide10",
			"Segments": [
				0,
				0,
				0,
				8.983,
				0
			]
		},
		{
			"Target": "Parameter",
			"Id": "ParamHairSide11",
			"Segments": [
				0,
				0,
				0,
				8.983,
				0
			]
		},
		{
			"Target": "Parameter",
			"Id": "Param9",
			"Segments": [
				0,
				0,
				0,
				7.983,
				0,
				1,
				8.317,
				0,
				8.65,
				0,
				8.983,
				0
			]
		},
		{
			"Target": "Parameter",
			"Id": "Param10",
			"Segments": [
				0,
				0,
				0,
				7.983,
				0,
				1,
				8.317,
				0,
				8.65,
				0,
				8.983,
				0
			]
		},
		{
			"Target": "Parameter",
			"Id": "Param11",
			"Segments": [
				0,
				0,
				0,
				7.983,
				0,
				1,
				8.317,
				0,
				8.65,
				0,
				8.983,
				0
			]
		},
		{
			"Target": "Parameter",
			"Id": "Param12",
			"Segments": [
				0,
				0,
				0,
				7.983,
				0,
				1,
				8.317,
				0,
				8.65,
				0,
				8.983,
				0
			]
		},
		{
			"Target": "Parameter",
			"Id": "Param3",
			"Segments": [
				0,
				0,
				0,
				7.983,
				0,
				1,
				8.317,
				0,
				8.65,
				0,
				8.983,
				0
			]
		},
		{
			"Target": "Parameter",
			"Id": "Param4",
			"Segments": [
				0,
				0,
				0,
				7.983,
				0,
				1,
				8.317,
				0,
				8.65,
				0,
				8.983,
				0
			]
		},
		{
			"Target": "Parameter",
			"Id": "Param17",
			"Segments": [
				0,
				0,
				0,
				7.983,
				0,
				1,
				8.317,
				0,
				8.65,
				0,
				8.983,
				0
			]
		},
		{
			"Target": "Parameter",
			"Id": "Param19",
			"Segments": [
				0,
				0,
				0,
				7.983,
				0,
				1,
				8.317,
				0,
				8.65,
				0,
				8.983,
				0
			]
		},
		{
			"Target": "Parameter",
			"Id": "Param18",
			"Segments": [
				0,
				0,
				0,
				7.983,
				0,
				1,
				8.317,
				0,
				8.65,
				0,
				8.983,
				0
			]
		},
		{
			"Target": "Parameter",
			"Id": "Param20",
			"Segments": [
				0,
				0,
				0,
				7.983,
				0,
				1,
				8.317,
				0,
				8.65,
				0,
				8.983,
				0
			]
		},
		{
			"Target": "Parameter",
			"Id": "ParamHairFront1",
			"Segments": [
				0,
				0,
				0,
				7.983,
				0,
				1,
				8.317,
				0,
				8.65,
				0,
				8.983,
				0
			]
		},
		{
			"Target": "Parameter",
			"Id": "ParamHairFront2",
			"Segments": [
				0,
				0,
				0,
				7.983,
				0,
				1,
				8.317,
				0,
				8.65,
				0,
				8.983,
				0
			]
		},
		{
			"Target": "Parameter",
			"Id": "ParamAngleX",
			"Segments": [
				0,
				0,
				1,
				0.156,
				0,
				0.311,
				-1.925,
				0.467,
				-1.925,
				1,
				0.983,
				-1.925,
				1.5,
				7.321,
				2.017,
				7.321,
				1,
				2.572,
				7.321,
				3.128,
				-7.476,
				3.683,
				-7.476,
				1,
				4.233,
				-7.476,
				4.783,
				3.904,
				5.333,
				3.904,
				1,
				6.217,
				3.904,
				7.1,
				0,
				7.983,
				0,
				1,
				8.317,
				0,
				8.65,
				0,
				8.983,
				0
			]
		},
		{
			"Target": "Parameter",
			"Id": "ParamAngleY",
			"Segments": [
				0,
				0,
				1,
				0.172,
				0,
				0.344,
				-4.506,
				0.517,
				-4.506,
				1,
				1.122,
				-4.506,
				1.728,
				9.387,
				2.333,
				9.387,
				1,
				2.778,
				9.387,
				3.222,
				-4.506,
				3.667,
				-4.506,
				1,
				4.15,
				-4.506,
				4.633,
				5.594,
				5.117,
				5.594,
				1,
				6.072,
				5.594,
				7.028,
				0,
				7.983,
				0,
				1,
				8.317,
				0,
				8.65,
				0,
				8.983,
				0
			]
		},
		{
			"Target": "Parameter",
			"Id": "ParamAngleZ",
			"Segments": [
				0,
				0,
				1,
				0.183,
				0,
				0.367,
				-2.51,
				0.55,
				-2.51,
				1,
				1.211,
				-2.51,
				1.872,
				5.84,
				2.533,
				5.84,
				1,
				3.122,
				5.84,
				3.711,
				-3.838,
				4.3,
				-3.838,
				1,
				5.528,
				-3.838,
				6.756,
				0,
				7.983,
				0,
				1,
				8.317,
				0,
				8.65,
				0,
				8.983,
				0
			]
		},
		{
			"Target": "Parameter",
			"Id": "ParamEyeLOpen",
			"Segments": [
				0,
				1,
				0,
				1.55,
				1,
				1,
				1.622,
				1,
				1.694,
				0,
				1.767,
				0,
				1,
				1.85,
				0,
				1.933,
				1,
				2.017,
				1,
				1,
				4.006,
				1,
				5.994,
				1,
				7.983,
				1,
				1,
				8.317,
				1,
				8.65,
				1,
				8.983,
				1
			]
		},
		{
			"Target": "Parameter",
			"Id": "ParamEyeLSmile",
			"Segments": [
				0,
				0,
				0,
				7.983,
				0,
				1,
				8.317,
				0,
				8.65,
				0,
				8.983,
				0
			]
		},
		{
			"Target": "Parameter",
			"Id": "ParamEyeROpen",
			"Segments": [
				0,
				1,
				0,
				1.567,
				1,
				1,
				1.633,
				1,
				1.7,
				0,
				1.767,
				0,
				1,
				1.844,
				0,
				1.922,
				1,
				2,
				1,
				1,
				3.994,
				1,
				5.989,
				1,
				7.983,
				1,
				1,
				8.317,
				1,
				8.65,
				1,
				8.983,
				1
			]
		},
		{
			"Target": "Parameter",
			"Id": "ParamEyeRSmile",
			"Segments": [
				0,
				0,
				0,
				7.983,
				0,
				1,
				8.317,
				0,
				8.65,
				0,
				8.983,
				0
			]
		},
		{
			"Target": "Parameter",
			"Id": "ParamEyeBallX",
			"Segments": [
				0,
				0,
				0,
				7.983,
				0,
				1,
				8.317,
				0,
				8.65,
				0,
				8.983,
				0
			]
		},
		{
			"Target": "Parameter",
			"Id": "ParamEyeBallY",
			"Segments": [
				0,
				0,
				0,
				7.983,
				0,
				1,
				8.317,
				0,
				8.65,
				0,
				8.983,
				0
			]
		},
		{
			"Target": "Parameter",
			"Id": "ParamBrowLY",
			"Segments": [
				0,
				0,
				0,
				7.983,
				0,
				1,
				8.317,
				0,
				8.65,
				0,
				8.983,
				0
			]
		},
		{
			"Target": "Parameter",
			"Id": "ParamBrowRY",
			"Segments": [
				0,
				0,
				0,
				7.983,
				0,
				1,
				8.317,
				0,
				8.65,
				0,
				8.983,
				0
			]
		},
		{
			"Target": "Parameter",
			"Id": "ParamBrowLX",
			"Segments": [
				0,
				0,
				0,
				7.983,
				0,
				1,
				8.317,
				0,
				8.65,
				0,
				8.983,
				0
			]
		},
		{
			"Target": "Parameter",
			"Id": "ParamBrowRX",
			"Segments": [
				0,
				0,
				0,
				7.983,
				0,
				1,
				8.317,
				0,
				8.65,
				0,
				8.983,
				0
			]
		},
		{
			"Target": "Parameter",
			"Id": "ParamBrowLAngle",
			"Segments": [
				0,
				0,
				0,
				7.983,
				0,
				1,
				8.317,
				0,
				8.65,
				0,
				8.983,
				0
			]
		},
		{
			"Target": "Parameter",
			"Id": "ParamBrowRAngle",
			"Segments": [
				0,
				0,
				0,
				7.983,
				0,
				1,
				8.317,
				0,
				8.65,
				0,
				8.983,
				0
			]
		},
		{
			"Target": "Parameter",
			"Id": "ParamBrowLForm",
			"Segments": [
				0,
				0,
				0,
				7.983,
				0,
				1,
				8.317,
				0,
				8.65,
				0,
				8.983,
				0
			]
		},
		{
			"Target": "Parameter",
			"Id": "ParamBrowRForm",
			"Segments": [
				0,
				0,
				0,
				7.983,
				0,
				1,
				8.317,
				0,
				8.65,
				0,
				8.983,
				0
			]
		},
		{
			"Target": "Parameter",
			"Id": "ParamCheek",
			"Segments": [
				0,
				0,
				0,
				7.983,
				0,
				1,
				8.317,
				0,
				8.65,
				0,
				8.983,
				0
			]
		},
		{
			"Target": "Parameter",
			"Id": "ParamBodyAngleX",
			"Segments": [
				0,
				0,
				1,
				0.789,
				0,
				1.578,
				1.28,
				2.367,
				1.28,
				1,
				3.122,
				1.28,
				3.878,
				-1.364,
				4.633,
				-1.364,
				1,
				5.75,
				-1.364,
				6.867,
				0,
				7.983,
				0,
				1,
				8.317,
				0,
				8.65,
				0,
				8.983,
				0
			]
		},
		{
			"Target": "Parameter",
			"Id": "ParamBodyAngleY",
			"Segments": [
				0,
				0,
				1,
				0.183,
				0,
				0.367,
				-0.041,
				0.55,
				-0.041,
				1,
				1.117,
				-0.041,
				1.683,
				0.099,
				2.25,
				0.099,
				1,
				3.056,
				0.099,
				3.861,
				-0.073,
				4.667,
				-0.073,
				1,
				5.772,
				-0.073,
				6.878,
				0,
				7.983,
				0,
				1,
				8.317,
				0,
				8.65,
				0,
				8.983,
				0
			]
		},
		{
			"Target": "Parameter",
			"Id": "ParamBodyAngleZ",
			"Segments": [
				0,
				0,
				1,
				0.256,
				0,
				0.511,
				-2.073,
				0.767,
				-2.073,
				1,
				1.45,
				-2.073,
				2.133,
				0,
				2.817,
				0,
				1,
				4.539,
				0,
				6.261,
				0,
				7.983,
				0,
				1,
				8.317,
				0,
				8.65,
				0,
				8.983,
				0
			]
		},
		{
			"Target": "Parameter",
			"Id": "ParamBreath",
			"Segments": [
				0,
				0,
				0,
				7.983,
				0,
				1,
				8.317,
				0,
				8.65,
				0,
				8.983,
				0
			]
		},
		{
			"Target": "Parameter",
			"Id": "ParamHairFront",
			"Segments": [
				0,
				0,
				0,
				7.983,
				0,
				1,
				8.317,
				0,
				8.65,
				0,
				8.983,
				0
			]
		},
		{
			"Target": "Parameter",
			"Id": "ParamHairSide",
			"Segments": [
				0,
				0,
				0,
				7.983,
				0,
				1,
				8.317,
				0,
				8.65,
				0,
				8.983,
				0
			]
		},
		{
			"Target": "Parameter",
			"Id": "ParamHairBack",
			"Segments": [
				0,
				0,
				0,
				7.983,
				0,
				1,
				8.317,
				0,
				8.65,
				0,
				8.983,
				0
			]
		}
	]
}
